[
  {
    "id": "1000001",
    "name": "Worker 1",
    "qualifications": [
      "Supervisor",
      "C&N Driver",
      "C&N Escort",
      "Southern Driver",
      "Southern Escort"
    ],
    "closing_interval": 3,
    "officer": false,
    "seniority": 0,
    "score": 33,
    "long_timer": false,
    "x_tasks": {},
    "y_tasks": {
      "2025-07-10": "Supervisor",
      "2025-07-11": "Supervisor",
      "2025-07-12": "Supervisor",
      "2025-07-16": "Supervisor",
      "2025-07-23": "Supervisor",
      "2025-07-30": "Supervisor",
      "2025-08-05": "Supervisor",
      "2025-08-11": "Supervisor",
      "2025-08-19": "Supervisor",
      "2025-08-27": "Supervisor",
      "2025-09-25": "Supervisor",
      "2025-09-26": "Supervisor",
      "2025-09-27": "Supervisor",
      "2025-09-17": "Supervisor",
      "2025-10-05": "Supervisor",
      "2025-10-07": "Supervisor",
      "2025-10-12": "Supervisor",
      "2025-10-21": "Supervisor",
      "2025-10-29": "Supervisor",
      "2025-11-02": "Supervisor",
      "2025-11-05": "Supervisor",
      "2025-12-18": "Supervisor",
      "2025-12-19": "Supervisor",
      "2025-12-20": "Supervisor"
    },
    "closing_history": []
  },
  {
    "id": "1000002",
    "name": "Worker 2",
    "qualifications": [
      "Supervisor",
      "C&N Driver",
      "C&N Escort",
      "Southern Driver",
      "Southern Escort"
    ],
    "closing_interval": 5,
    "officer": false,
    "seniority": 0,
    "score": 33,
    "long_timer": false,
    "x_tasks": {},
    "y_tasks": {
      "2025-07-10": "C&N Driver",
      "2025-07-11": "C&N Driver",
      "2025-07-12": "C&N Driver",
      "2025-07-16": "C&N Driver",
      "2025-07-23": "C&N Driver",
      "2025-07-30": "C&N Driver",
      "2025-08-05": "C&N Driver",
      "2025-08-11": "C&N Driver",
      "2025-08-19": "C&N Driver",
      "2025-08-27": "C&N Driver",
      "2025-09-25": "C&N Driver",
      "2025-09-26": "C&N Driver",
      "2025-09-27": "C&N Driver",
      "2025-09-17": "C&N Driver",
      "2025-10-05": "C&N Driver",
      "2025-10-07": "C&N Driver",
      "2025-10-12": "C&N Driver",
      "2025-10-21": "C&N Driver",
      "2025-10-29": "C&N Driver",
      "2025-11-02": "C&N Driver",
      "2025-11-05": "C&N Driver",
      "2025-12-18": "C&N Driver",
      "2025-12-19": "C&N Driver",
      "2025-12-20": "C&N Driver"
    },
    "closing_history": []
  },
  {
    "id": "1000003",
    "name": "Worker 3",
    "qualifications": [
      "Supervisor",
      "C&N Driver",
      "C&N Escort",
      "Southern Driver",
      "Southern Escort"
    ],
    "closing_interval": 5,
    "officer": false,
    "seniority": 0,
    "score": 33,
    "long_timer": false,
    "x_tasks": {},
    "y_tasks": {
      "2025-07-10": "C&N Escort",
      "2025-07-11": "C&N Escort",
      "2025-07-12": "C&N Escort",
      "2025-07-16": "C&N Escort",
      "2025-07-23": "C&N Escort",
      "2025-07-30": "C&N Escort",
      "2025-08-05": "C&N Escort",
      "2025-08-11": "C&N Escort",
      "2025-08-19": "C&N Escort",
      "2025-08-27": "C&N Escort",
      "2025-09-25": "C&N Escort",
      "2025-09-26": "C&N Escort",
      "2025-09-27": "C&N Escort",
      "2025-09-17": "C&N Escort",
      "2025-10-05": "C&N Escort",
      "2025-10-07": "C&N Escort",
      "2025-10-12": "C&N Escort",
      "2025-10-21": "C&N Escort",
      "2025-10-29": "C&N Escort",
      "2025-11-02": "C&N Escort",
      "2025-11-05": "C&N Escort",
      "2025-12-18": "C&N Escort",
      "2025-12-19": "C&N Escort",
      "2025-12-20": "C&N Escort"
    },
    "closing_history": []
  },
  {
    "id": "1000004",
    "name": "Worker 4",
    "qualifications": [
      "Supervisor",
      "C&N Driver",
      "C&N Escort",
      "Southern Driver",
      "Southern Escort"
    ],
    "closing_interval": 3,
    "officer": false,
    "seniority": 0,
    "score": 33,
    "long_timer": false,
    "x_tasks": {},
    "y_tasks": {
      "2025-07-10": "Southern Driver",
      "2025-07-11": "Southern Driver",
      "2025-07-12": "Southern Driver",
      "2025-07-16": "Southern Driver",
      "2025-07-23": "Southern Driver",
      "2025-07-30": "Southern Driver",
      "2025-08-05": "Southern Driver",
      "2025-08-11": "Southern Driver",
      "2025-08-19": "Southern Driver",
      "2025-08-27": "Southern Driver",
      "2025-09-25": "Southern Driver",
      "2025-09-26": "Southern Driver",
      "2025-09-27": "Southern Driver",
      "2025-09-17": "Southern Driver",
      "2025-10-05": "Southern Driver",
      "2025-10-07": "Southern Driver",
      "2025-10-12": "Southern Driver",
      "2025-10-21": "Southern Driver",
      "2025-10-29": "Southern Driver",
      "2025-11-02": "Southern Driver",
      "2025-11-05": "Southern Driver",
      "2025-12-18": "Southern Driver",
      "2025-12-19": "Southern Driver",
      "2025-12-20": "Southern Driver"
    },
    "closing_history": []
  },
  {
    "id": "1000005",
    "name": "Worker 5",
    "qualifications": [
      "Supervisor",
      "C&N Driver",
      "C&N Escort",
      "Southern Driver",
      "Southern Escort"
    ],
    "closing_interval": 4,
    "officer": false,
    "seniority": 0,
    "score": 33,
    "long_timer": false,
    "x_tasks": {},
    "y_tasks": {
      "2025-07-10": "Southern Escort",
      "2025-07-11": "Southern Escort",
      "2025-07-12": "Southern Escort",
      "2025-07-16": "Southern Escort",
      "2025-07-23": "Southern Escort",
      "2025-07-30": "Southern Escort",
      "2025-08-05": "Southern Escort",
      "2025-08-11": "Southern Escort",
      "2025-08-19": "Southern Escort",
      "2025-08-27": "Southern Escort",
      "2025-09-25": "Southern Escort",
      "2025-09-26": "Southern Escort",
      "2025-09-27": "Southern Escort",
      "2025-09-17": "Southern Escort",
      "2025-10-05": "Southern Escort",
      "2025-10-07": "Southern Escort",
      "2025-10-12": "Southern Escort",
      "2025-10-21": "Southern Escort",
      "2025-10-29": "Southern Escort",
      "2025-11-02": "Southern Escort",
      "2025-11-05": "Southern Escort",
      "2025-12-18": "Southern Escort",
      "2025-12-19": "Southern Escort",
      "2025-12-20": "Southern Escort"
    },
    "closing_history": []
  },
  {
    "id": "1000006",
    "name": "Worker 6",
    "qualifications": [
      "Supervisor",
      "C&N Driver",
      "C&N Escort",
      "Southern Driver",
      "Southern Escort"
    ],
    "closing_interval": 5,
    "officer": false,
    "seniority": 0,
    "score": 52,
    "long_timer": false,
    "x_tasks": {},
    "y_tasks": {
      "2025-07-17": "Supervisor",
      "2025-07-18": "Supervisor",
      "2025-07-19": "Supervisor",
      "2025-07-06": "Supervisor",
      "2025-07-07": "Supervisor",
      "2025-07-20": "Supervisor",
      "2025-07-21": "Supervisor",
      "2025-07-27": "Supervisor",
      "2025-07-28": "Supervisor",
      "2025-08-31": "Supervisor",
      "2025-09-01": "Supervisor",
      "2025-09-28": "Supervisor",
      "2025-09-29": "Supervisor",
      "2025-11-06": "Supervisor",
      "2025-11-07": "Supervisor",
      "2025-11-08": "Supervisor",
      "2025-11-20": "Supervisor",
      "2025-11-21": "Supervisor",
      "2025-11-22": "Supervisor",
      "2025-11-23": "Supervisor",
      "2025-11-26": "Supervisor",
      "2025-12-14": "Supervisor"
    },
    "closing_history": []
  },
  {
    "id": "1000007",
    "name": "Worker 7",
    "qualifications": [
      "Supervisor",
      "C&N Driver",
      "C&N Escort",
      "Southern Driver",
      "Southern Escort"
    ],
    "closing_interval": 3,
    "officer": false,
    "seniority": 0,
    "score": 52,
    "long_timer": false,
    "x_tasks": {},
    "y_tasks": {
      "2025-07-17": "C&N Driver",
      "2025-07-18": "C&N Driver",
      "2025-07-19": "C&N Driver",
      "2025-07-06": "C&N Driver",
      "2025-07-07": "C&N Driver",
      "2025-07-20": "C&N Driver",
      "2025-07-21": "C&N Driver",
      "2025-07-27": "C&N Driver",
      "2025-07-28": "C&N Driver",
      "2025-08-31": "C&N Driver",
      "2025-09-01": "C&N Driver",
      "2025-09-28": "C&N Driver",
      "2025-09-29": "C&N Driver",
      "2025-11-06": "C&N Driver",
      "2025-11-07": "C&N Driver",
      "2025-11-08": "C&N Driver",
      "2025-11-20": "C&N Driver",
      "2025-11-21": "C&N Driver",
      "2025-11-22": "C&N Driver",
      "2025-11-23": "C&N Driver",
      "2025-11-26": "C&N Driver",
      "2025-12-14": "C&N Driver"
    },
    "closing_history": []
  },
  {
    "id": "1000008",
    "name": "Worker 8",
    "qualifications": [
      "Supervisor",
      "C&N Driver",
      "C&N Escort",
      "Southern Driver",
      "Southern Escort"
    ],
    "closing_interval": 4,
    "officer": false,
    "seniority": 0,
    "score": 52,
    "long_timer": false,
    "x_tasks": {},
    "y_tasks": {
      "2025-07-17": "C&N Escort",
      "2025-07-18": "C&N Escort",
      "2025-07-19": "C&N Escort",
      "2025-07-06": "C&N Escort",
      "2025-07-07": "C&N Escort",
      "2025-07-20": "C&N Escort",
      "2025-07-21": "C&N Escort",
      "2025-07-27": "C&N Escort",
      "2025-07-28": "C&N Escort",
      "2025-08-31": "C&N Escort",
      "2025-09-01": "C&N Escort",
      "2025-09-28": "C&N Escort",
      "2025-09-29": "C&N Escort",
      "2025-11-06": "C&N Escort",
      "2025-11-07": "C&N Escort",
      "2025-11-08": "C&N Escort",
      "2025-11-20": "C&N Escort",
      "2025-11-21": "C&N Escort",
      "2025-11-22": "C&N Escort",
      "2025-11-23": "C&N Escort",
      "2025-11-26": "C&N Escort",
      "2025-12-14": "C&N Escort"
    },
    "closing_history": []
  },
  {
    "id": "1000009",
    "name": "Worker 9",
    "qualifications": [
      "Supervisor",
      "C&N Driver",
      "C&N Escort",
      "Southern Driver",
      "Southern Escort"
    ],
    "closing_interval": 5,
    "officer": false,
    "seniority": 0,
    "score": 52,
    "long_timer": false,
    "x_tasks": {},
    "y_tasks": {
      "2025-07-17": "Southern Driver",
      "2025-07-18": "Southern Driver",
      "2025-07-19": "Southern Driver",
      "2025-07-06": "Southern Driver",
      "2025-07-07": "Southern Driver",
      "2025-07-20": "Southern Driver",
      "2025-07-21": "Southern Driver",
      "2025-07-27": "Southern Driver",
      "2025-07-28": "Southern Driver",
      "2025-08-31": "Southern Driver",
      "2025-09-01": "Southern Driver",
      "2025-09-28": "Southern Driver",
      "2025-09-29": "Southern Driver",
      "2025-11-06": "Southern Driver",
      "2025-11-07": "Southern Driver",
      "2025-11-08": "Southern Driver",
      "2025-11-20": "Southern Driver",
      "2025-11-21": "Southern Driver",
      "2025-11-22": "Southern Driver",
      "2025-11-23": "Southern Driver",
      "2025-11-26": "Southern Driver",
      "2025-12-14": "Southern Driver"
    },
    "closing_history": []
  },
  {
    "id": "1000010",
    "name": "Worker 10",
    "qualifications": [
      "Supervisor",
      "C&N Driver",
      "C&N Escort",
      "Southern Driver",
      "Southern Escort"
    ],
    "closing_interval": 6,
    "officer": false,
    "seniority": 0,
    "score": 52,
    "long_timer": false,
    "x_tasks": {},
    "y_tasks": {
      "2025-07-17": "Southern Escort",
      "2025-07-18": "Southern Escort",
      "2025-07-19": "Southern Escort",
      "2025-07-06": "Southern Escort",
      "2025-07-07": "Southern Escort",
      "2025-07-20": "Southern Escort",
      "2025-07-21": "Southern Escort",
      "2025-07-27": "Southern Escort",
      "2025-07-28": "Southern Escort",
      "2025-08-31": "Southern Escort",
      "2025-09-01": "Southern Escort",
      "2025-09-28": "Southern Escort",
      "2025-09-29": "Southern Escort",
      "2025-11-06": "Southern Escort",
      "2025-11-07": "Southern Escort",
      "2025-11-08": "Southern Escort",
      "2025-11-20": "Southern Escort",
      "2025-11-21": "Southern Escort",
      "2025-11-22": "Southern Escort",
      "2025-11-23": "Southern Escort",
      "2025-11-26": "Southern Escort",
      "2025-12-14": "Southern Escort"
    },
    "closing_history": []
  },
  {
    "id": "1000011",
    "name": "Worker 11",
    "qualifications": [
      "Supervisor",
      "C&N Driver",
      "C&N Escort",
      "Southern Driver",
      "Southern Escort"
    ],
    "closing_interval": 3,
    "officer": false,
    "seniority": 0,
    "score": 38,
    "long_timer": false,
    "x_tasks": {},
    "y_tasks": {
      "2025-07-24": "Supervisor",
      "2025-07-25": "Supervisor",
      "2025-07-26": "Supervisor",
      "2025-07-08": "Supervisor",
      "2025-07-13": "Supervisor",
      "2025-07-14": "Supervisor",
      "2025-07-29": "Supervisor",
      "2025-09-02": "Supervisor",
      "2025-09-30": "Supervisor",
      "2025-09-08": "Supervisor",
      "2025-09-14": "Supervisor",
      "2025-09-23": "Supervisor",
      "2025-10-16": "Supervisor",
      "2025-10-17": "Supervisor",
      "2025-10-18": "Supervisor",
      "2025-10-19": "Supervisor",
      "2025-10-27": "Supervisor",
      "2025-11-03": "Supervisor",
      "2025-11-10": "Supervisor",
      "2025-11-17": "Supervisor",
      "2025-11-24": "Supervisor",
      "2025-12-08": "Supervisor",
      "2025-12-16": "Supervisor"
    },
    "closing_history": []
  },
  {
    "id": "1000012",
    "name": "Worker 12",
    "qualifications": [
      "Supervisor",
      "C&N Driver",
      "C&N Escort",
      "Southern Driver",
      "Southern Escort"
    ],
    "closing_interval": 6,
    "officer": false,
    "seniority": 0,
    "score": 38,
    "long_timer": false,
    "x_tasks": {},
    "y_tasks": {
      "2025-07-24": "C&N Driver",
      "2025-07-25": "C&N Driver",
      "2025-07-26": "C&N Driver",
      "2025-07-08": "C&N Driver",
      "2025-07-13": "C&N Driver",
      "2025-07-14": "C&N Driver",
      "2025-07-29": "C&N Driver",
      "2025-09-02": "C&N Driver",
      "2025-09-30": "C&N Driver",
      "2025-09-08": "C&N Driver",
      "2025-09-14": "C&N Driver",
      "2025-09-23": "C&N Driver",
      "2025-10-16": "C&N Driver",
      "2025-10-17": "C&N Driver",
      "2025-10-18": "C&N Driver",
      "2025-10-19": "C&N Driver",
      "2025-10-27": "C&N Driver",
      "2025-11-03": "C&N Driver",
      "2025-11-10": "C&N Driver",
      "2025-11-17": "C&N Driver",
      "2025-11-24": "C&N Driver",
      "2025-12-08": "C&N Driver",
      "2025-12-16": "C&N Driver"
    },
    "closing_history": []
  },
  {
    "id": "1000013",
    "name": "Worker 13",
    "qualifications": [
      "Supervisor",
      "C&N Driver",
      "C&N Escort",
      "Southern Driver",
      "Southern Escort"
    ],
    "closing_interval": 5,
    "officer": false,
    "seniority": 0,
    "score": 38,
    "long_timer": false,
    "x_tasks": {},
    "y_tasks": {
      "2025-07-24": "C&N Escort",
      "2025-07-25": "C&N Escort",
      "2025-07-26": "C&N Escort",
      "2025-07-08": "C&N Escort",
      "2025-07-13": "C&N Escort",
      "2025-07-14": "C&N Escort",
      "2025-07-29": "C&N Escort",
      "2025-09-02": "C&N Escort",
      "2025-09-30": "C&N Escort",
      "2025-09-08": "C&N Escort",
      "2025-09-14": "C&N Escort",
      "2025-09-23": "C&N Escort",
      "2025-10-16": "C&N Escort",
      "2025-10-17": "C&N Escort",
      "2025-10-18": "C&N Escort",
      "2025-10-19": "C&N Escort",
      "2025-10-27": "C&N Escort",
      "2025-11-03": "C&N Escort",
      "2025-11-10": "C&N Escort",
      "2025-11-17": "C&N Escort",
      "2025-11-24": "C&N Escort",
      "2025-12-08": "C&N Escort",
      "2025-12-16": "C&N Escort"
    },
    "closing_history": []
  },
  {
    "id": "1000014",
    "name": "Worker 14",
    "qualifications": [
      "Supervisor",
      "C&N Driver",
      "C&N Escort",
      "Southern Driver",
      "Southern Escort"
    ],
    "closing_interval": 5,
    "officer": false,
    "seniority": 0,
    "score": 38,
    "long_timer": false,
    "x_tasks": {},
    "y_tasks": {
      "2025-07-24": "Southern Driver",
      "2025-07-25": "Southern Driver",
      "2025-07-26": "Southern Driver",
      "2025-07-08": "Southern Driver",
      "2025-07-13": "Southern Driver",
      "2025-07-14": "Southern Driver",
      "2025-07-29": "Southern Driver",
      "2025-09-02": "Southern Driver",
      "2025-09-30": "Southern Driver",
      "2025-09-08": "Southern Driver",
      "2025-09-14": "Southern Driver",
      "2025-09-23": "Southern Driver",
      "2025-10-16": "Southern Driver",
      "2025-10-17": "Southern Driver",
      "2025-10-18": "Southern Driver",
      "2025-10-19": "Southern Driver",
      "2025-10-27": "Southern Driver",
      "2025-11-03": "Southern Driver",
      "2025-11-10": "Southern Driver",
      "2025-11-17": "Southern Driver",
      "2025-11-24": "Southern Driver",
      "2025-12-08": "Southern Driver",
      "2025-12-16": "Southern Driver"
    },
    "closing_history": []
  },
  {
    "id": "1000015",
    "name": "Worker 15",
    "qualifications": [
      "Supervisor",
      "C&N Driver",
      "C&N Escort",
      "Southern Driver",
      "Southern Escort"
    ],
    "closing_interval": 6,
    "officer": false,
    "seniority": 0,
    "score": 38,
    "long_timer": false,
    "x_tasks": {},
    "y_tasks": {
      "2025-07-24": "Southern Escort",
      "2025-07-25": "Southern Escort",
      "2025-07-26": "Southern Escort",
      "2025-07-08": "Southern Escort",
      "2025-07-13": "Southern Escort",
      "2025-07-14": "Southern Escort",
      "2025-07-29": "Southern Escort",
      "2025-09-02": "Southern Escort",
      "2025-09-30": "Southern Escort",
      "2025-09-08": "Southern Escort",
      "2025-09-14": "Southern Escort",
      "2025-09-23": "Southern Escort",
      "2025-10-16": "Southern Escort",
      "2025-10-17": "Southern Escort",
      "2025-10-18": "Southern Escort",
      "2025-10-19": "Southern Escort",
      "2025-10-27": "Southern Escort",
      "2025-11-03": "Southern Escort",
      "2025-11-10": "Southern Escort",
      "2025-11-17": "Southern Escort",
      "2025-11-24": "Southern Escort",
      "2025-12-08": "Southern Escort",
      "2025-12-16": "Southern Escort"
    },
    "closing_history": []
  },
  {
    "id": "1000016",
    "name": "Worker 16",
    "qualifications": [
      "Supervisor",
      "C&N Driver",
      "C&N Escort",
      "Southern Driver",
      "Southern Escort"
    ],
    "closing_interval": 4,
    "officer": false,
    "seniority": 0,
    "score": 38,
    "long_timer": false,
    "x_tasks": {},
    "y_tasks": {
      "2025-07-31": "Supervisor",
      "2025-08-01": "Supervisor",
      "2025-08-02": "Supervisor",
      "2025-07-09": "Supervisor",
      "2025-07-15": "Supervisor",
      "2025-07-22": "Supervisor",
      "2025-09-03": "Supervisor",
      "2025-10-01": "Supervisor",
      "2025-09-07": "Supervisor",
      "2025-09-09": "Supervisor",
      "2025-09-15": "Supervisor",
      "2025-09-24": "Supervisor",
      "2025-10-23": "Supervisor",
      "2025-10-24": "Supervisor",
      "2025-10-25": "Supervisor",
      "2025-10-26": "Supervisor",
      "2025-10-28": "Supervisor",
      "2025-11-04": "Supervisor",
      "2025-11-11": "Supervisor",
      "2025-11-18": "Supervisor",
      "2025-11-25": "Supervisor",
      "2025-12-09": "Supervisor",
      "2025-12-17": "Supervisor"
    },
    "closing_history": []
  },
  {
    "id": "1000017",
    "name": "Worker 17",
    "qualifications": [
      "Supervisor",
      "C&N Driver",
      "C&N Escort",
      "Southern Driver",
      "Southern Escort"
    ],
    "closing_interval": 6,
    "officer": false,
    "seniority": 0,
    "score": 38,
    "long_timer": false,
    "x_tasks": {},
    "y_tasks": {
      "2025-07-31": "C&N Driver",
      "2025-08-01": "C&N Driver",
      "2025-08-02": "C&N Driver",
      "2025-07-09": "C&N Driver",
      "2025-07-15": "C&N Driver",
      "2025-07-22": "C&N Driver",
      "2025-09-03": "C&N Driver",
      "2025-10-01": "C&N Driver",
      "2025-09-07": "C&N Driver",
      "2025-09-09": "C&N Driver",
      "2025-09-15": "C&N Driver",
      "2025-09-24": "C&N Driver",
      "2025-10-23": "C&N Driver",
      "2025-10-24": "C&N Driver",
      "2025-10-25": "C&N Driver",
      "2025-10-26": "C&N Driver",
      "2025-10-28": "C&N Driver",
      "2025-11-04": "C&N Driver",
      "2025-11-11": "C&N Driver",
      "2025-11-18": "C&N Driver",
      "2025-11-25": "C&N Driver",
      "2025-12-09": "C&N Driver",
      "2025-12-17": "C&N Driver"
    },
    "closing_history": []
  },
  {
    "id": "1000018",
    "name": "Worker 18",
    "qualifications": [
      "Supervisor",
      "C&N Driver",
      "C&N Escort",
      "Southern Driver",
      "Southern Escort"
    ],
    "closing_interval": 3,
    "officer": false,
    "seniority": 0,
    "score": 38,
    "long_timer": false,
    "x_tasks": {},
    "y_tasks": {
      "2025-07-31": "C&N Escort",
      "2025-08-01": "C&N Escort",
      "2025-08-02": "C&N Escort",
      "2025-07-09": "C&N Escort",
      "2025-07-15": "C&N Escort",
      "2025-07-22": "C&N Escort",
      "2025-09-03": "C&N Escort",
      "2025-10-01": "C&N Escort",
      "2025-09-07": "C&N Escort",
      "2025-09-09": "C&N Escort",
      "2025-09-15": "C&N Escort",
      "2025-09-24": "C&N Escort",
      "2025-10-23": "C&N Escort",
      "2025-10-24": "C&N Escort",
      "2025-10-25": "C&N Escort",
      "2025-10-26": "C&N Escort",
      "2025-10-28": "C&N Escort",
      "2025-11-04": "C&N Escort",
      "2025-11-11": "C&N Escort",
      "2025-11-18": "C&N Escort",
      "2025-11-25": "C&N Escort",
      "2025-12-09": "C&N Escort",
      "2025-12-17": "C&N Escort"
    },
    "closing_history": []
  },
  {
    "id": "1000019",
    "name": "Worker 19",
    "qualifications": [
      "Supervisor",
      "C&N Driver",
      "C&N Escort",
      "Southern Driver",
      "Southern Escort"
    ],
    "closing_interval": 6,
    "officer": false,
    "seniority": 0,
    "score": 38,
    "long_timer": false,
    "x_tasks": {},
    "y_tasks": {
      "2025-07-31": "Southern Driver",
      "2025-08-01": "Southern Driver",
      "2025-08-02": "Southern Driver",
      "2025-07-09": "Southern Driver",
      "2025-07-15": "Southern Driver",
      "2025-07-22": "Southern Driver",
      "2025-09-03": "Southern Driver",
      "2025-10-01": "Southern Driver",
      "2025-09-07": "Southern Driver",
      "2025-09-09": "Southern Driver",
      "2025-09-15": "Southern Driver",
      "2025-09-24": "Southern Driver",
      "2025-10-23": "Southern Driver",
      "2025-10-24": "Southern Driver",
      "2025-10-25": "Southern Driver",
      "2025-10-26": "Southern Driver",
      "2025-10-28": "Southern Driver",
      "2025-11-04": "Southern Driver",
      "2025-11-11": "Southern Driver",
      "2025-11-18": "Southern Driver",
      "2025-11-25": "Southern Driver",
      "2025-12-09": "Southern Driver",
      "2025-12-17": "Southern Driver"
    },
    "closing_history": []
  },
  {
    "id": "1000020",
    "name": "Worker 20",
    "qualifications": [
      "Supervisor",
      "C&N Driver",
      "C&N Escort",
      "Southern Driver",
      "Southern Escort"
    ],
    "closing_interval": 6,
    "officer": false,
    "seniority": 0,
    "score": 38,
    "long_timer": false,
    "x_tasks": {},
    "y_tasks": {
      "2025-07-31": "Southern Escort",
      "2025-08-01": "Southern Escort",
      "2025-08-02": "Southern Escort",
      "2025-07-09": "Southern Escort",
      "2025-07-15": "Southern Escort",
      "2025-07-22": "Southern Escort",
      "2025-09-03": "Southern Escort",
      "2025-10-01": "Southern Escort",
      "2025-09-07": "Southern Escort",
      "2025-09-09": "Southern Escort",
      "2025-09-15": "Southern Escort",
      "2025-09-24": "Southern Escort",
      "2025-10-23": "Southern Escort",
      "2025-10-24": "Southern Escort",
      "2025-10-25": "Southern Escort",
      "2025-10-26": "Southern Escort",
      "2025-10-28": "Southern Escort",
      "2025-11-04": "Southern Escort",
      "2025-11-11": "Southern Escort",
      "2025-11-18": "Southern Escort",
      "2025-11-25": "Southern Escort",
      "2025-12-09": "Southern Escort",
      "2025-12-17": "Southern Escort"
    },
    "closing_history": []
  },
  {
    "id": "1000021",
    "name": "Worker 21",
    "qualifications": [
      "Supervisor",
      "C&N Driver",
      "C&N Escort",
      "Southern Driver",
      "Southern Escort"
    ],
    "closing_interval": 5,
    "officer": false,
    "seniority": 0,
    "score": 37,
    "long_timer": false,
    "x_tasks": {},
    "y_tasks": {
      "2025-08-14": "Supervisor",
      "2025-08-15": "Supervisor",
      "2025-08-16": "Supervisor",
      "2025-08-03": "Supervisor",
      "2025-08-04": "Supervisor",
      "2025-08-17": "Supervisor",
      "2025-08-18": "Supervisor",
      "2025-08-24": "Supervisor",
      "2025-08-26": "Supervisor",
      "2025-09-11": "Supervisor",
      "2025-09-12": "Supervisor",
      "2025-09-13": "Supervisor",
      "2025-09-16": "Supervisor",
      "2025-10-30": "Supervisor",
      "2025-10-31": "Supervisor",
      "2025-10-08": "Supervisor",
      "2025-10-15": "Supervisor",
      "2025-11-09": "Supervisor",
      "2025-11-27": "Supervisor",
      "2025-11-28": "Supervisor",
      "2025-11-29": "Supervisor",
      "2025-12-10": "Supervisor"
    },
    "closing_history": []
  },
  {
    "id": "1000022",
    "name": "Worker 22",
    "qualifications": [
      "Supervisor",
      "C&N Driver",
      "C&N Escort",
      "Southern Driver",
      "Southern Escort"
    ],
    "closing_interval": 6,
    "officer": false,
    "seniority": 0,
    "score": 37,
    "long_timer": false,
    "x_tasks": {},
    "y_tasks": {
      "2025-08-14": "C&N Driver",
      "2025-08-15": "C&N Driver",
      "2025-08-16": "C&N Driver",
      "2025-08-03": "C&N Driver",
      "2025-08-04": "C&N Driver",
      "2025-08-17": "C&N Driver",
      "2025-08-18": "C&N Driver",
      "2025-08-24": "C&N Driver",
      "2025-08-26": "C&N Driver",
      "2025-09-11": "C&N Driver",
      "2025-09-12": "C&N Driver",
      "2025-09-13": "C&N Driver",
      "2025-09-16": "C&N Driver",
      "2025-10-30": "C&N Driver",
      "2025-10-31": "C&N Driver",
      "2025-10-08": "C&N Driver",
      "2025-10-15": "C&N Driver",
      "2025-11-09": "C&N Driver",
      "2025-11-27": "C&N Driver",
      "2025-11-28": "C&N Driver",
      "2025-11-29": "C&N Driver",
      "2025-12-10": "C&N Driver"
    },
    "closing_history": []
  },
  {
    "id": "1000023",
    "name": "Worker 23",
    "qualifications": [
      "Supervisor",
      "C&N Driver",
      "C&N Escort",
      "Southern Driver",
      "Southern Escort"
    ],
    "closing_interval": 4,
    "officer": false,
    "seniority": 0,
    "score": 37,
    "long_timer": false,
    "x_tasks": {},
    "y_tasks": {
      "2025-08-14": "C&N Escort",
      "2025-08-15": "C&N Escort",
      "2025-08-16": "C&N Escort",
      "2025-08-03": "C&N Escort",
      "2025-08-04": "C&N Escort",
      "2025-08-17": "C&N Escort",
      "2025-08-18": "C&N Escort",
      "2025-08-24": "C&N Escort",
      "2025-08-26": "C&N Escort",
      "2025-09-11": "C&N Escort",
      "2025-09-12": "C&N Escort",
      "2025-09-13": "C&N Escort",
      "2025-09-16": "C&N Escort",
      "2025-10-30": "C&N Escort",
      "2025-10-31": "C&N Escort",
      "2025-10-08": "C&N Escort",
      "2025-10-15": "C&N Escort",
      "2025-11-09": "C&N Escort",
      "2025-11-27": "C&N Escort",
      "2025-11-28": "C&N Escort",
      "2025-11-29": "C&N Escort",
      "2025-12-10": "C&N Escort"
    },
    "closing_history": []
  },
  {
    "id": "1000024",
    "name": "Worker 24",
    "qualifications": [
      "Supervisor",
      "C&N Driver",
      "C&N Escort",
      "Southern Driver",
      "Southern Escort"
    ],
    "closing_interval": 5,
    "officer": false,
    "seniority": 0,
    "score": 37,
    "long_timer": false,
    "x_tasks": {},
    "y_tasks": {
      "2025-08-14": "Southern Driver",
      "2025-08-15": "Southern Driver",
      "2025-08-16": "Southern Driver",
      "2025-08-03": "Southern Driver",
      "2025-08-04": "Southern Driver",
      "2025-08-17": "Southern Driver",
      "2025-08-18": "Southern Driver",
      "2025-08-24": "Southern Driver",
      "2025-08-26": "Southern Driver",
      "2025-09-11": "Southern Driver",
      "2025-09-12": "Southern Driver",
      "2025-09-13": "Southern Driver",
      "2025-09-16": "Southern Driver",
      "2025-10-30": "Southern Driver",
      "2025-10-31": "Southern Driver",
      "2025-10-08": "Southern Driver",
      "2025-10-15": "Southern Driver",
      "2025-11-09": "Southern Driver",
      "2025-11-27": "Southern Driver",
      "2025-11-28": "Southern Driver",
      "2025-11-29": "Southern Driver",
      "2025-12-10": "Southern Driver"
    },
    "closing_history": []
  },
  {
    "id": "1000025",
    "name": "Worker 25",
    "qualifications": [
      "Supervisor",
      "C&N Driver",
      "C&N Escort",
      "Southern Driver",
      "Southern Escort"
    ],
    "closing_interval": 3,
    "officer": false,
    "seniority": 0,
    "score": 37,
    "long_timer": false,
    "x_tasks": {},
    "y_tasks": {
      "2025-08-14": "Southern Escort",
      "2025-08-15": "Southern Escort",
      "2025-08-16": "Southern Escort",
      "2025-08-03": "Southern Escort",
      "2025-08-04": "Southern Escort",
      "2025-08-17": "Southern Escort",
      "2025-08-18": "Southern Escort",
      "2025-08-24": "Southern Escort",
      "2025-08-26": "Southern Escort",
      "2025-09-11": "Southern Escort",
      "2025-09-12": "Southern Escort",
      "2025-09-13": "Southern Escort",
      "2025-09-16": "Southern Escort",
      "2025-10-30": "Southern Escort",
      "2025-10-31": "Southern Escort",
      "2025-10-08": "Southern Escort",
      "2025-10-15": "Southern Escort",
      "2025-11-09": "Southern Escort",
      "2025-11-27": "Southern Escort",
      "2025-11-28": "Southern Escort",
      "2025-11-29": "Southern Escort",
      "2025-12-10": "Southern Escort"
    },
    "closing_history": []
  },
  {
    "id": "1000026",
    "name": "Worker 26",
    "qualifications": [
      "Supervisor",
      "C&N Driver",
      "C&N Escort",
      "Southern Driver",
      "Southern Escort"
    ],
    "closing_interval": 5,
    "officer": false,
    "seniority": 0,
    "score": 32,
    "long_timer": false,
    "x_tasks": {},
    "y_tasks": {
      "2025-09-04": "Supervisor",
      "2025-09-05": "Supervisor",
      "2025-09-06": "Supervisor",
      "2025-10-02": "Supervisor",
      "2025-10-03": "Supervisor",
      "2025-10-04": "Supervisor",
      "2025-11-01": "Supervisor",
      "2025-08-21": "Supervisor",
      "2025-08-22": "Supervisor",
      "2025-08-23": "Supervisor",
      "2025-08-06": "Supervisor",
      "2025-08-12": "Supervisor",
      "2025-08-25": "Supervisor",
      "2025-09-10": "Supervisor",
      "2025-09-22": "Supervisor",
      "2025-10-06": "Supervisor",
      "2025-10-13": "Supervisor",
      "2025-10-20": "Supervisor",
      "2025-11-12": "Supervisor",
      "2025-11-16": "Supervisor",
      "2025-11-19": "Supervisor",
      "2025-12-11": "Supervisor",
      "2025-12-12": "Supervisor",
      "2025-12-13": "Supervisor"
    },
    "closing_history": []
  },
  {
    "id": "1000027",
    "name": "Worker 27",
    "qualifications": [
      "Supervisor",
      "C&N Driver",
      "C&N Escort",
      "Southern Driver",
      "Southern Escort"
    ],
    "closing_interval": 3,
    "officer": false,
    "seniority": 0,
    "score": 32,
    "long_timer": false,
    "x_tasks": {},
    "y_tasks": {
      "2025-09-04": "C&N Driver",
      "2025-09-05": "C&N Driver",
      "2025-09-06": "C&N Driver",
      "2025-10-02": "C&N Driver",
      "2025-10-03": "C&N Driver",
      "2025-10-04": "C&N Driver",
      "2025-11-01": "C&N Driver",
      "2025-08-21": "C&N Driver",
      "2025-08-22": "C&N Driver",
      "2025-08-23": "C&N Driver",
      "2025-08-06": "C&N Driver",
      "2025-08-12": "C&N Driver",
      "2025-08-25": "C&N Driver",
      "2025-09-10": "C&N Driver",
      "2025-09-22": "C&N Driver",
      "2025-10-06": "C&N Driver",
      "2025-10-13": "C&N Driver",
      "2025-10-20": "C&N Driver",
      "2025-11-12": "C&N Driver",
      "2025-11-16": "C&N Driver",
      "2025-11-19": "C&N Driver",
      "2025-12-11": "C&N Driver",
      "2025-12-12": "C&N Driver",
      "2025-12-13": "C&N Driver"
    },
    "closing_history": []
  },
  {
    "id": "1000028",
    "name": "Worker 28",
    "qualifications": [
      "Supervisor",
      "C&N Driver",
      "C&N Escort",
      "Southern Driver",
      "Southern Escort"
    ],
    "closing_interval": 3,
    "officer": false,
    "seniority": 0,
    "score": 32,
    "long_timer": false,
    "x_tasks": {},
    "y_tasks": {
      "2025-09-04": "C&N Escort",
      "2025-09-05": "C&N Escort",
      "2025-09-06": "C&N Escort",
      "2025-10-02": "C&N Escort",
      "2025-10-03": "C&N Escort",
      "2025-10-04": "C&N Escort",
      "2025-11-01": "C&N Escort",
      "2025-08-21": "C&N Escort",
      "2025-08-22": "C&N Escort",
      "2025-08-23": "C&N Escort",
      "2025-08-06": "C&N Escort",
      "2025-08-12": "C&N Escort",
      "2025-08-25": "C&N Escort",
      "2025-09-10": "C&N Escort",
      "2025-09-22": "C&N Escort",
      "2025-10-06": "C&N Escort",
      "2025-10-13": "C&N Escort",
      "2025-10-20": "C&N Escort",
      "2025-11-12": "C&N Escort",
      "2025-11-16": "C&N Escort",
      "2025-11-19": "C&N Escort",
      "2025-12-11": "C&N Escort",
      "2025-12-12": "C&N Escort",
      "2025-12-13": "C&N Escort"
    },
    "closing_history": []
  },
  {
    "id": "1000029",
    "name": "Worker 29",
    "qualifications": [
      "Supervisor",
      "C&N Driver",
      "C&N Escort",
      "Southern Driver",
      "Southern Escort"
    ],
    "closing_interval": 3,
    "officer": false,
    "seniority": 0,
    "score": 32,
    "long_timer": false,
    "x_tasks": {},
    "y_tasks": {
      "2025-09-04": "Southern Driver",
      "2025-09-05": "Southern Driver",
      "2025-09-06": "Southern Driver",
      "2025-10-02": "Southern Driver",
      "2025-10-03": "Southern Driver",
      "2025-10-04": "Southern Driver",
      "2025-11-01": "Southern Driver",
      "2025-08-21": "Southern Driver",
      "2025-08-22": "Southern Driver",
      "2025-08-23": "Southern Driver",
      "2025-08-06": "Southern Driver",
      "2025-08-12": "Southern Driver",
      "2025-08-25": "Southern Driver",
      "2025-09-10": "Southern Driver",
      "2025-09-22": "Southern Driver",
      "2025-10-06": "Southern Driver",
      "2025-10-13": "Southern Driver",
      "2025-10-20": "Southern Driver",
      "2025-11-12": "Southern Driver",
      "2025-11-16": "Southern Driver",
      "2025-11-19": "Southern Driver",
      "2025-12-11": "Southern Driver",
      "2025-12-12": "Southern Driver",
      "2025-12-13": "Southern Driver"
    },
    "closing_history": []
  },
  {
    "id": "1000030",
    "name": "Worker 30",
    "qualifications": [
      "Supervisor",
      "C&N Driver",
      "C&N Escort",
      "Southern Driver",
      "Southern Escort"
    ],
    "closing_interval": 4,
    "officer": false,
    "seniority": 0,
    "score": 32,
    "long_timer": false,
    "x_tasks": {},
    "y_tasks": {
      "2025-09-04": "Southern Escort",
      "2025-09-05": "Southern Escort",
      "2025-09-06": "Southern Escort",
      "2025-10-02": "Southern Escort",
      "2025-10-03": "Southern Escort",
      "2025-10-04": "Southern Escort",
      "2025-11-01": "Southern Escort",
      "2025-08-21": "Southern Escort",
      "2025-08-22": "Southern Escort",
      "2025-08-23": "Southern Escort",
      "2025-08-06": "Southern Escort",
      "2025-08-12": "Southern Escort",
      "2025-08-25": "Southern Escort",
      "2025-09-10": "Southern Escort",
      "2025-09-22": "Southern Escort",
      "2025-10-06": "Southern Escort",
      "2025-10-13": "Southern Escort",
      "2025-10-20": "Southern Escort",
      "2025-11-12": "Southern Escort",
      "2025-11-16": "Southern Escort",
      "2025-11-19": "Southern Escort",
      "2025-12-11": "Southern Escort",
      "2025-12-12": "Southern Escort",
      "2025-12-13": "Southern Escort"
    },
    "closing_history": []
  },
  {
    "id": "1000031",
    "name": "Worker 31",
    "qualifications": [
      "Supervisor",
      "C&N Driver",
      "C&N Escort",
      "Southern Driver",
      "Southern Escort"
    ],
    "closing_interval": 4,
    "officer": false,
    "seniority": 0,
    "score": 35,
    "long_timer": false,
    "x_tasks": {},
    "y_tasks": {
      "2025-08-07": "Supervisor",
      "2025-08-08": "Supervisor",
      "2025-08-09": "Supervisor",
      "2025-08-28": "Supervisor",
      "2025-08-29": "Supervisor",
      "2025-08-30": "Supervisor",
      "2025-08-10": "Supervisor",
      "2025-08-13": "Supervisor",
      "2025-08-20": "Supervisor",
      "2025-09-18": "Supervisor",
      "2025-09-19": "Supervisor",
      "2025-09-20": "Supervisor",
      "2025-09-21": "Supervisor",
      "2025-10-09": "Supervisor",
      "2025-10-10": "Supervisor",
      "2025-10-11": "Supervisor",
      "2025-10-14": "Supervisor",
      "2025-10-22": "Supervisor",
      "2025-11-13": "Supervisor",
      "2025-11-14": "Supervisor",
      "2025-11-15": "Supervisor",
      "2025-12-07": "Supervisor",
      "2025-12-15": "Supervisor"
    },
    "closing_history": []
  },
  {
    "id": "1000032",
    "name": "Worker 32",
    "qualifications": [
      "Supervisor",
      "C&N Driver",
      "C&N Escort",
      "Southern Driver",
      "Southern Escort"
    ],
    "closing_interval": 3,
    "officer": false,
    "seniority": 0,
    "score": 35,
    "long_timer": false,
    "x_tasks": {},
    "y_tasks": {
      "2025-08-07": "C&N Driver",
      "2025-08-08": "C&N Driver",
      "2025-08-09": "C&N Driver",
      "2025-08-28": "C&N Driver",
      "2025-08-29": "C&N Driver",
      "2025-08-30": "C&N Driver",
      "2025-08-10": "C&N Driver",
      "2025-08-13": "C&N Driver",
      "2025-08-20": "C&N Driver",
      "2025-09-18": "C&N Driver",
      "2025-09-19": "C&N Driver",
      "2025-09-20": "C&N Driver",
      "2025-09-21": "C&N Driver",
      "2025-10-09": "C&N Driver",
      "2025-10-10": "C&N Driver",
      "2025-10-11": "C&N Driver",
      "2025-10-14": "C&N Driver",
      "2025-10-22": "C&N Driver",
      "2025-11-13": "C&N Driver",
      "2025-11-14": "C&N Driver",
      "2025-11-15": "C&N Driver",
      "2025-12-07": "C&N Driver",
      "2025-12-15": "C&N Driver"
    },
    "closing_history": []
  },
  {
    "id": "1000033",
    "name": "Worker 33",
    "qualifications": [
      "Supervisor",
      "C&N Driver",
      "C&N Escort",
      "Southern Driver",
      "Southern Escort"
    ],
    "closing_interval": 4,
    "officer": false,
    "seniority": 0,
    "score": 35,
    "long_timer": false,
    "x_tasks": {},
    "y_tasks": {
      "2025-08-07": "C&N Escort",
      "2025-08-08": "C&N Escort",
      "2025-08-09": "C&N Escort",
      "2025-08-28": "C&N Escort",
      "2025-08-29": "C&N Escort",
      "2025-08-30": "C&N Escort",
      "2025-08-10": "C&N Escort",
      "2025-08-13": "C&N Escort",
      "2025-08-20": "C&N Escort",
      "2025-09-18": "C&N Escort",
      "2025-09-19": "C&N Escort",
      "2025-09-20": "C&N Escort",
      "2025-09-21": "C&N Escort",
      "2025-10-09": "C&N Escort",
      "2025-10-10": "C&N Escort",
      "2025-10-11": "C&N Escort",
      "2025-10-14": "C&N Escort",
      "2025-10-22": "C&N Escort",
      "2025-11-13": "C&N Escort",
      "2025-11-14": "C&N Escort",
      "2025-11-15": "C&N Escort",
      "2025-12-07": "C&N Escort",
      "2025-12-15": "C&N Escort"
    },
    "closing_history": []
  },
  {
    "id": "1000034",
    "name": "Worker 34",
    "qualifications": [
      "Supervisor",
      "C&N Driver",
      "C&N Escort",
      "Southern Driver",
      "Southern Escort"
    ],
    "closing_interval": 4,
    "officer": false,
    "seniority": 0,
    "score": 35,
    "long_timer": false,
    "x_tasks": {},
    "y_tasks": {
      "2025-08-07": "Southern Driver",
      "2025-08-08": "Southern Driver",
      "2025-08-09": "Southern Driver",
      "2025-08-28": "Southern Driver",
      "2025-08-29": "Southern Driver",
      "2025-08-30": "Southern Driver",
      "2025-08-10": "Southern Driver",
      "2025-08-13": "Southern Driver",
      "2025-08-20": "Southern Driver",
      "2025-09-18": "Southern Driver",
      "2025-09-19": "Southern Driver",
      "2025-09-20": "Southern Driver",
      "2025-09-21": "Southern Driver",
      "2025-10-09": "Southern Driver",
      "2025-10-10": "Southern Driver",
      "2025-10-11": "Southern Driver",
      "2025-10-14": "Southern Driver",
      "2025-10-22": "Southern Driver",
      "2025-11-13": "Southern Driver",
      "2025-11-14": "Southern Driver",
      "2025-11-15": "Southern Driver",
      "2025-12-07": "Southern Driver",
      "2025-12-15": "Southern Driver"
    },
    "closing_history": []
  },
  {
    "id": "1000035",
    "name": "Worker 35",
    "qualifications": [
      "Supervisor",
      "C&N Driver",
      "C&N Escort",
      "Southern Driver",
      "Southern Escort"
    ],
    "closing_interval": 4,
    "officer": false,
    "seniority": 0,
    "score": 35,
    "long_timer": false,
    "x_tasks": {},
    "y_tasks": {
      "2025-08-07": "Southern Escort",
      "2025-08-08": "Southern Escort",
      "2025-08-09": "Southern Escort",
      "2025-08-28": "Southern Escort",
      "2025-08-29": "Southern Escort",
      "2025-08-30": "Southern Escort",
      "2025-08-10": "Southern Escort",
      "2025-08-13": "Southern Escort",
      "2025-08-20": "Southern Escort",
      "2025-09-18": "Southern Escort",
      "2025-09-19": "Southern Escort",
      "2025-09-20": "Southern Escort",
      "2025-09-21": "Southern Escort",
      "2025-10-09": "Southern Escort",
      "2025-10-10": "Southern Escort",
      "2025-10-11": "Southern Escort",
      "2025-10-14": "Southern Escort",
      "2025-10-22": "Southern Escort",
      "2025-11-13": "Southern Escort",
      "2025-11-14": "Southern Escort",
      "2025-11-15": "Southern Escort",
      "2025-12-07": "Southern Escort",
      "2025-12-15": "Southern Escort"
    },
    "closing_history": []
  }
]